qtune/__init__.py
qtune/analyzer.py
qtune/autotuner.py
qtune/basic_dqd.py
qtune/evaluator.py
qtune/experiment.py
qtune/gradient.py
qtune/gui.py
qtune/history.py
qtune/kalman_gradient.py
qtune/kalman_heuristics.py
qtune/mat2py.py
qtune/parameter_tuner.py
qtune/sm.py
qtune/sm_tune_qqd.py
qtune/solver.py
qtune/storage.py
qtune/util.py
qtune-0.1.0.dist-info/METADATA
qtune-0.1.0.dist-info/RECORD
qtune-0.1.0.dist-info/WHEEL
qtune-0.1.0.dist-info/top_level.txt
