Metadata-Version: 2.1
Name: qtune
Version: 0.1.0
Summary: Quantum dot auto tune framework
Home-page: https://github.com/qutech/qtune
Author: RWTH Aachen Quantum Technology Group
Author-email: julian.teske@rwth-aachen.de
License: GNU GPLv3+
Keywords: autotune quantum
Platform: UNKNOWN
Classifier: Development Status :: 3 - Alpha
Classifier: Intended Audience :: Science/Research
Classifier: Topic :: Scientific/Engineering :: Physics
Classifier: License :: OSI Approved :: GNU General Public License v3 or later (GPLv3+)
Requires-Dist: pandas
Requires-Dist: numpy
Requires-Dist: filterpy
Requires-Dist: scipy
Requires-Dist: h5py
Requires-Dist: sympy
